parplot/__init__.py
parplot/__main__.py
parplot/cli.py
parplot-0.1.2.dist-info/METADATA
parplot-0.1.2.dist-info/WHEEL
parplot-0.1.2.dist-info/entry_points.txt
parplot-0.1.2.dist-info/RECORD
